crossdb
