Metadata-Version: 1.0
Name: django-crossdb
Version: 0.1.2
Summary: Tools for enabling Django models to relate to each other across databases.
Home-page: http://bitbucket.org/gazetteer/django-crossdb
Author: Eric Shull
Author-email: eric.shull@gmail.com
License: BSD
Keywords: django
Platform: UNKNOWN
